comdirect_api/__init__.py
comdirect_api/auth.py
comdirect_api/client.py
comdirect_api/exceptions.py
comdirect_api/utils.py
comdirect_api/domain/__init__.py
comdirect_api/domain/mappers.py
comdirect_api/domain/models.py
comdirect_api_wrapper-0.3.1.dist-info/licenses/LICENSE
openapi_client/__init__.py
openapi_client/api_client.py
openapi_client/api_response.py
openapi_client/configuration.py
openapi_client/exceptions.py
openapi_client/py.typed
openapi_client/rest.py
openapi_client/api/__init__.py
openapi_client/api/banking_api.py
openapi_client/api/brokerage_api.py
openapi_client/api/messages_api.py
openapi_client/api/reports_api.py
openapi_client/api/session_api.py
openapi_client/models/__init__.py
openapi_client/models/account.py
openapi_client/models/account_balance.py
openapi_client/models/account_information.py
openapi_client/models/account_transaction.py
openapi_client/models/amount_value.py
openapi_client/models/balance.py
openapi_client/models/business_message.py
openapi_client/models/card.py
openapi_client/models/card_balance.py
openapi_client/models/cost_entry.py
openapi_client/models/cost_group.py
openapi_client/models/cost_indication_ex_ante.py
openapi_client/models/depot.py
openapi_client/models/depot_aggregation.py
openapi_client/models/depot_position.py
openapi_client/models/depot_transaction.py
openapi_client/models/derivative_data.py
openapi_client/models/dimensions.py
openapi_client/models/document.py
openapi_client/models/document_metadata.py
openapi_client/models/enum_text.py
openapi_client/models/execution.py
openapi_client/models/fixed_term_savings.py
openapi_client/models/fund_distribution.py
openapi_client/models/fx_rate_eur.py
openapi_client/models/inducement.py
openapi_client/models/installment_loan.py
openapi_client/models/installment_loan_balance.py
openapi_client/models/instrument.py
openapi_client/models/list_resource_account_balance.py
openapi_client/models/list_resource_account_transaction.py
openapi_client/models/list_resource_cost_indication_ex_ante.py
comdirect_api_wrapper-0.3.1.dist-info/METADATA
comdirect_api_wrapper-0.3.1.dist-info/WHEEL
comdirect_api_wrapper-0.3.1.dist-info/top_level.txt
comdirect_api_wrapper-0.3.1.dist-info/RECORD
