Metadata-Version: 2.4
Name: comdirect_api_wrapper
Version: 0.3.1
Summary: Python module for comdirect REST api
Author-email: Michael Adams <m@ad4ms.de>
License: MIT
Project-URL: Bug Reports, https://github.com/mad4ms/comdirect-api-wrapper/issues
Project-URL: Source, https://github.com/mad4ms/comdirect-api-wrapper/
Keywords: comdirect,rest,api
Classifier: Development Status :: 3 - Alpha
Classifier: Intended Audience :: Developers
Classifier: Topic :: Software Development :: Build Tools
Classifier: Programming Language :: Python :: 3
Classifier: Programming Language :: Python :: 3.12
Requires-Python: >=3.12
License-File: LICENSE
Requires-Dist: pillow
Requires-Dist: requests
Requires-Dist: urllib3<3.0.0,>=1.25.3
Requires-Dist: python-dateutil
Requires-Dist: pydantic>2
Requires-Dist: typing-extensions
Requires-Dist: mcp>=1.25.0
Provides-Extra: dev
Requires-Dist: flake8; extra == "dev"
Requires-Dist: black; extra == "dev"
Requires-Dist: pre-commit; extra == "dev"
Requires-Dist: pytest; extra == "dev"
Requires-Dist: build; extra == "dev"
Requires-Dist: python-dotenv; extra == "dev"
Requires-Dist: openapi-generator-cli>=7.18.0; extra == "dev"
Dynamic: license-file
